taproom/__init__.py
taproom/_version.py
taproom/entry_points.py
taproom/systems/acd/MGO.mol2
taproom/systems/acd/acd.mol2
taproom/systems/acd/acd.pdb
taproom/systems/acd/build_acd.in
taproom/systems/acd/build_acd.sh
taproom/systems/acd/host-p.yaml
taproom/systems/acd/host-s.yaml
taproom/systems/acd/bam/a-bam-p.pdb
taproom/systems/acd/bam/a-bam-s.pdb
taproom/systems/acd/bam/bam.mol2
taproom/systems/acd/bam/guest.yaml
taproom/systems/acd/bam/measurement.yaml
taproom/systems/acd/but/a-but-p.pdb
taproom/systems/acd/but/a-but-s.pdb
taproom/systems/acd/but/but.mol2
taproom/systems/acd/but/guest.yaml
taproom/systems/acd/but/measurement.yaml
taproom/systems/acd/cbu/a-cbu-p.pdb
taproom/systems/acd/cbu/a-cbu-s.pdb
taproom/systems/acd/cbu/cbu.mol2
taproom/systems/acd/cbu/guest.yaml
taproom/systems/acd/cbu/measurement.yaml
taproom/systems/acd/chp/a-chp-p.pdb
taproom/systems/acd/chp/a-chp-s.pdb
taproom/systems/acd/chp/chp.mol2
taproom/systems/acd/chp/guest.yaml
taproom/systems/acd/chp/measurement.yaml
taproom/systems/acd/coc/a-coc-p.pdb
taproom/systems/acd/coc/a-coc-s.pdb
taproom/systems/acd/coc/coc.mol2
taproom/systems/acd/coc/guest.yaml
taproom/systems/acd/coc/measurement.yaml
taproom/systems/acd/cpe/a-cpe-p.pdb
taproom/systems/acd/cpe/a-cpe-s.pdb
taproom/systems/acd/cpe/cpe.mol2
taproom/systems/acd/cpe/guest.yaml
taproom/systems/acd/cpe/measurement.yaml
taproom/systems/acd/ham/a-ham-p.pdb
taproom/systems/acd/ham/a-ham-s.pdb
taproom/systems/acd/ham/guest.yaml
taproom/systems/acd/ham/ham.mol2
taproom/systems/acd/ham/measurement.yaml
taproom/systems/acd/hep/a-hep-p.pdb
taproom/systems/acd/hep/a-hep-s.pdb
taproom/systems/acd/hep/guest.yaml
taproom/systems/acd/hep/hep.mol2
taproom/systems/acd/hep/measurement.yaml
taproom/systems/acd/hex/a-hex-p.pdb
taproom/systems/acd/hex/a-hex-s.pdb
taproom/systems/acd/hex/guest.yaml
taproom/systems/acd/hex/hex.mol2
taproom/systems/acd/hex/measurement.yaml
taproom/systems/acd/hp6/a-hp6-p.pdb
taproom/systems/acd/hp6/a-hp6-s.pdb
taproom-0.2.dist-info/LICENSE
taproom-0.2.dist-info/METADATA
taproom-0.2.dist-info/WHEEL
taproom-0.2.dist-info/entry_points.txt
taproom-0.2.dist-info/top_level.txt
taproom-0.2.dist-info/RECORD
