Metadata-Version: 2.1
Name: taproom
Version: 0.2
Summary: UNKNOWN
Home-page: UNKNOWN
Author: David R. Slochower
Author-email: slochower@gmail.com
License: MIT
Platform: UNKNOWN
